mrg32k3a_numba/__init__.py
mrg32k3a_numba/mrg32k3a_numba.py
mrg32k3a_numba-1.0.0.dist-info/licenses/LICENSE
mrg32k3a_numba-1.0.0.dist-info/METADATA
mrg32k3a_numba-1.0.0.dist-info/WHEEL
mrg32k3a_numba-1.0.0.dist-info/top_level.txt
mrg32k3a_numba-1.0.0.dist-info/RECORD
