Metadata-Version: 2.4
Name: mrg32k3a_numba
Version: 1.0.0
Summary: An accelerated version of the MRG32k3a generator using Numba for high-performance operations.
Author-email: Song Huang <23b910018@stu.hit.edu.cn>, Guangxin Jiang <gxjiang@hit.edu.cn>, Ying Zhong <yzhong4@uestc.edu.cn>
License: MIT License
Project-URL: Homepage, https://github.com/simulation-optimization/mrg32k3a-numba
Project-URL: Bug Tracker, https://github.com/simulation-optimization/mrg32k3a-numba/issues
Keywords: random number generator,rng,mrg32k3a,numba,simulation
Classifier: Development Status :: 4 - Beta
Classifier: Programming Language :: Python :: 3
Classifier: License :: OSI Approved :: MIT License
Classifier: Operating System :: OS Independent
Classifier: Intended Audience :: Science/Research
Classifier: Intended Audience :: Developers
Classifier: Topic :: Scientific/Engineering
Classifier: Topic :: Software Development :: Libraries :: Python Modules
Requires-Python: >=3.8
License-File: LICENSE
Requires-Dist: numpy
Requires-Dist: numba
Requires-Dist: mrg32k3a
Dynamic: license-file
